nnstorm_cloud/__init__.py
nnstorm_cloud/azure/__init__.py
nnstorm_cloud/azure/api.py
nnstorm_cloud/azure/cred_wrapper.py
nnstorm_cloud/azure/keyvault.py
nnstorm_cloud/azure/manager.py
nnstorm_cloud/azure/virtual_machine.py
nnstorm_cloud/core/__init__.py
nnstorm_cloud/core/utils.py
nnstorm_cloud/kubernetes/__init__.py
nnstorm_cloud/kubernetes/helm.py
nnstorm_cloud/kubernetes/kubectl.py
nnstorm_cloud-0.4.5.data/scripts/nnstorm-vm
nnstorm_cloud-0.4.5.dist-info/LICENSE
nnstorm_cloud-0.4.5.dist-info/METADATA
nnstorm_cloud-0.4.5.dist-info/WHEEL
nnstorm_cloud-0.4.5.dist-info/top_level.txt
nnstorm_cloud-0.4.5.dist-info/RECORD
