Metadata-Version: 2.1
Name: nnstorm-cloud
Version: 0.4.5
Summary: NNstorm cloud automation
Home-page: https://github.com/NNstorm/nnstorm-cloud
Author: Geza Velkey
Author-email: geza@nnstorm.com
License: UNKNOWN
Platform: UNKNOWN
Classifier: Programming Language :: Python :: 3
Classifier: Programming Language :: Python :: 3.7
Classifier: Programming Language :: Python :: 3.8
Classifier: Programming Language :: Python :: 3.9
Classifier: Operating System :: OS Independent
Requires-Python: >=3.7
Requires-Dist: azure-cli-core (==2.15.1)
Requires-Dist: azure-common (==1.1.26)
Requires-Dist: azure-core (==1.9.0)
Requires-Dist: azure-cosmos (==4.2.0)
Requires-Dist: azure-cosmosdb-nspkg (==2.0.2)
Requires-Dist: azure-cosmosdb-table (==1.0.6)
Requires-Dist: azure-graphrbac (==0.61.1)
Requires-Dist: azure-identity (==1.3.1)
Requires-Dist: azure-keyvault (==4.1.0)
Requires-Dist: azure-keyvault-certificates (==4.2.1)
Requires-Dist: azure-keyvault-keys (==4.3.0)
Requires-Dist: azure-keyvault-secrets (==4.2.0)
Requires-Dist: azure-mgmt-compute (==18.0.0)
Requires-Dist: azure-mgmt-containerservice (==10.1.0)
Requires-Dist: azure-mgmt-core (==1.2.1)
Requires-Dist: azure-mgmt-dns (==3.0.0)
Requires-Dist: azure-mgmt-keyvault (==8.0.0)
Requires-Dist: azure-mgmt-network (==16.0.0)
Requires-Dist: azure-mgmt-privatedns (==0.1.0)
Requires-Dist: azure-mgmt-rdbms (==2.2.0)
Requires-Dist: azure-mgmt-resource (==10.2.0)
Requires-Dist: azure-mgmt-storage (==16.0.0)
Requires-Dist: azure-storage-blob (==12.6.0)
Requires-Dist: azure-storage-common (==2.1.0)
Requires-Dist: azure-storage-file (==2.1.0)
Requires-Dist: coloredlogs
Requires-Dist: pytest
Requires-Dist: pytest-parallel
